setup.py
table_driver/__init__.py
table_driver/api.py
table_driver.egg-info/PKG-INFO
table_driver.egg-info/SOURCES.txt
table_driver.egg-info/dependency_links.txt
table_driver.egg-info/not-zip-safe
table_driver.egg-info/requires.txt
table_driver.egg-info/top_level.txt