Metadata-Version: 2.1
Name: table-driver
Version: 0.0.2
Summary: Table driver.
Home-page: https://github.com/drivernet/table_driver
Author: Mindey
Author-email: mindey@qq.com
License: ASK FOR PERMISSIONS
Platform: UNKNOWN
Provides-Extra: test
